{
"correctSolutions": [{"path": "$TASK_PATH/tests/gen/sol-ok-c.h", "language": "c", "grade": 100}],
"defaultEvaluationSolutions": [{
    "id": "@solutionId",
    "compilationDescr": {
        "language": "c",
        "files": [{"name": "runner.c",
                   "path": "$TASK_PATH/tests/gen/runner.c"}],
        "dependencies": [{"name": "solution.h",
                          "path": "@solutionPath",
                          "content": "@solutionContent"}]
        },
    "compilationExecution": "@defaultSolutionCompParams"}]
}
